[
  {
    "date": "25122025",
    "reunions": [
      {
        "numOfficiel": 1,
        "hippodrome": {
          "nom": "Réunion 1",
          "ville": "",
          "codePostal": ""
        },
        "typeReunion": "PLAT",
        "pays": {
          "code": "FRA",
          "libelle": "FRANCE"
        },
        "courses": [
          {
            "numOrdre": 1,
            "heureDepart": 1766665380000,
            "libelleCourt": "CHATELLERAULT",
            "distance": 2850,
            "discipline": "ATTELE"
          },
          {
            "numOrdre": 2,
            "heureDepart": 1766667720000,
            "libelleCourt": "CASTELSARRASIN",
            "distance": 2850,
            "discipline": "ATTELE"
          },
          {
            "numOrdre": 3,
            "heureDepart": 1766669700000,
            "libelleCourt": "DE GRIMAULT",
            "distance": 2700,
            "discipline": "MONTE"
          },
          {
            "numOrdre": 4,
            "heureDepart": 1766672100000,
            "libelleCourt": "ST-AUBIN-LES-E.",
            "distance": 2700,
            "discipline": "ATTELE"
          },
          {
            "numOrdre": 5,
            "heureDepart": 1766674200000,
            "libelleCourt": "DE LA TOURAINE",
            "distance": 2700,
            "discipline": "ATTELE"
          },
          {
            "numOrdre": 6,
            "heureDepart": 1766676300000,
            "libelleCourt": "DE SAUTRON",
            "distance": 2175,
            "discipline": "MONTE"
          },
          {
            "numOrdre": 7,
            "heureDepart": 1766677980000,
            "libelleCourt": "CHATEAU CHINON",
            "distance": 2700,
            "discipline": "ATTELE"
          },
          {
            "numOrdre": 8,
            "heureDepart": 1766679480000,
            "libelleCourt": "DEUIL-LA-BARRE",
            "distance": 2700,
            "discipline": "ATTELE"
          }
        ]
      },
      {
        "numOfficiel": 2,
        "hippodrome": {
          "nom": "Réunion 2",
          "ville": "",
          "codePostal": ""
        },
        "typeReunion": "PLAT",
        "pays": {
          "code": "FRA",
          "libelle": "FRANCE"
        },
        "courses": [
          {
            "numOrdre": 1,
            "heureDepart": 1766662200000,
            "libelleCourt": "LOIC AUDON",
            "distance": 3800,
            "discipline": "STEEPLECHASE"
          },
          {
            "numOrdre": 2,
            "heureDepart": 1766664180000,
            "libelleCourt": "DE L'ESTERON",
            "distance": 4000,
            "discipline": "HAIE"
          },
          {
            "numOrdre": 3,
            "heureDepart": 1766666400000,
            "libelleCourt": "DE BIRMINGHAM",
            "distance": 3400,
            "discipline": "HAIE"
          },
          {
            "numOrdre": 4,
            "heureDepart": 1766668680000,
            "libelleCourt": "DU CAP CAMARAT",
            "distance": 3400,
            "discipline": "HAIE"
          },
          {
            "numOrdre": 5,
            "heureDepart": 1766670600000,
            "libelleCourt": "DE L'AQUITAINE",
            "distance": 3700,
            "discipline": "STEEPLECHASE"
          },
          {
            "numOrdre": 6,
            "heureDepart": 1766673120000,
            "libelleCourt": "DU CAP ROUX",
            "distance": 4000,
            "discipline": "HAIE"
          },
          {
            "numOrdre": 7,
            "heureDepart": 1766675220000,
            "libelleCourt": "DU CAP FERRAT",
            "distance": 3400,
            "discipline": "HAIE"
          }
        ]
      }
    ]
  }
]